{
  "date": "2026-03-13",
  "selectionCriteria": "① 내일도 영향이 남는 이슈 ② 과도한 감정 소모 제외 ③ 어제와 중복되는 뉴스 제외",
  "editorNote": "이 뉴스는 클릭 수가 아니라 오늘 이후에도 남는 정보만 기준으로 편집했습니다.",
  "question": "정보를 덜 보는 것이 오히려 더 똑똑한 소비일까?",
  "lastUpdatedAt": "2026-03-13T07:57:19.053750+09:00",
  "items": [
    {
      "id": "2026-03-13_1",
      "date": "2026-03-13",
      "category": "국제",
      "title": "미국 동아태 차관보 방한, 관세·안보 협상 속도 맞춰 이행 논의",
      "summary": [
        "마이클 디솜브리 미국 국무부 동아시아·태평양 차관보가 방한하여 대미 투자 및 안보 협상의 빠른 이행에 대한 공감대를 형성했습니다.",
        "양측은 핵잠수함 추진과 원자력 등 안보 분야 협상을 관세 협상과 균형을 맞춰 진행해야 한다는 데 뜻을 같이했습니다.",
        "외교부는 미국 무역대표부(USTR)의 조사 대상에 한국이 포함된 데 대한 우려를 전달했습니다."
      ],
      "whyImportant": "한미 간의 관세 및 안보 협상 진행 방향은 양국 관계 및 관련 산업에 중요한 영향을 미칠 수 있습니다.",
      "importanceRationale": "근거: 3500달러 규모의 대미투자특별법 통과와 USTR 조사 대상에 한국 포함에 대한 논의가 있었으며, 3월 안으로 첫 안보 협상을 목표로 하고 있어 중요도 3으로 판단됩니다.",
      "impactSignals": [
        {
          "label": "policy",
          "evidence": "한국을 방문 중인 마이클 디솜브리 미국 국무부 동아시아·태평양 차관보는 12일 국회를 통과한 대미투자특별법 처리를 환영하며, 한·미 정상이 합의한 조인트 팩트시트(공동 설명자료)에 따른 대미 투자·안보 협상을 보다 빠르게 이행해 나가자는 데 공감대를 이뤘다."
        }
      ],
      "dedupeKey": "관세-동아태-미국-방한-속도-안보-차관보-협상",
      "clusterKey": "한미_법집행/동아태/투자/관세",
      "matchedTo": null,
      "sourceName": "한겨레",
      "sourceUrl": "https://www.hani.co.kr/arti/politics/politics_general/1249095.html",
      "publishedAt": "2026-03-12T12:04:00+00:00",
      "readTimeSec": 10,
      "status": "kept",
      "importance": 3,
      "qualityLabel": "ok",
      "qualityReason": "정보성 기사",
      "isBriefing": false
    },
    {
      "id": "2026-03-13_2",
      "date": "2026-03-13",
      "category": "기술",
      "title": "엔비디아, 오픈 소스 AI 모델 구축에 260억 달러 투자",
      "summary": [
        "엔비디아가 향후 5년간 오픈 소스 인공지능 모델 구축에 260억 달러를 투자할 예정입니다.",
        "이번 투자를 통해 엔비디아는 칩 제조업체를 넘어 AI 분야의 선두 주자로 도약할 수 있습니다.",
        "엔비디아는 N 3 S 라는 최신 오픈 웨이트 AI 모델을 공개했습니다."
      ],
      "whyImportant": "엔비디아의 대규모 투자는 AI 모델 개발 경쟁 심화 및 관련 기술 발전에 장기적인 영향을 미칠 수 있습니다.",
      "importanceRationale": "근거: 엔비디아가 향후 5년간 260억 달러를 투자하여 오픈 소스 AI 모델을 구축할 계획이며, 이는 AI 생태계 발전에 기여할 수 있습니다.",
      "impactSignals": [
        {
          "label": "capex",
          "evidence": "Nvidia will spend $26 billion over the next five years to build open source artificial intelligence models, according to a 2025 financial filing."
        }
      ],
      "dedupeKey": "260억-구축-달러-모델-소스-엔비디아-오픈-투자",
      "clusterKey": "투자/ai/엔비디아",
      "matchedTo": null,
      "sourceName": "WIRED",
      "sourceUrl": "https://www.wired.com/story/nvidia-investing-26-billion-open-source-models/",
      "publishedAt": "2026-03-11T18:00:00+00:00",
      "readTimeSec": 10,
      "status": "kept",
      "importance": 4,
      "qualityLabel": "ok",
      "qualityReason": "정보성 기사",
      "isBriefing": false
    },
    {
      "id": "2026-03-13_3",
      "date": "2026-03-13",
      "category": "에너지",
      "title": "기후부, 이란발 고유가 대비 원전·석탄화력 가동률 제고",
      "summary": [
        "정부는 이란발 고유가 장기화에 대비해 원자력 및 석탄화력 발전 가동률을 높이기로 했습니다.",
        "액화천연가스 수급 차질 시 석탄발전을 활용하고, 재생에너지 보급 확대를 추진할 예정입니다."
      ],
      "whyImportant": "에너지 수입 의존도가 높은 한국이 국제 에너지 가격 변동에 대응하고 에너지 안보를 강화하는 데 중요한 결정입니다.",
      "importanceRationale": "근거: 고유가 장기화에 대비해 원전 2기를 이달 내 재가동하고, 5월 중순까지 4기를 추가 재가동하며 석탄발전 활용 방안을 검토하는 등 에너지 정책 변화를 시사합니다.",
      "impactSignals": [
        {
          "label": "market-demand",
          "evidence": "김 장관은 “우리나라 에너지 시스템은 수입 화석연료 의존도가 높아 국제 에너지 가격 변동에 취약하다”며 “재생에너지 중심의 에너지 구조로 신속히 전환하는 것은 에너지의 수입 의존도와 탈탄소를 동시에 해결하는 에너지 안보의 핵심”이라고 밝혔다."
        },
        {
          "label": "capex",
          "evidence": "기후부는 “황사와 미세먼지 영향이 적은 시기를 골라 석탄발전의 가동률을 높이고, 저유황탄 사용과 대기오염방지시설 가동 확대 등으로 발전량이 늘어나도 미세먼지 배출이 급격히 늘지 않도록 관리하겠다”고 밝혔다."
        },
        {
          "label": "policy",
          "evidence": "이에 올해 재생에너지 보급과 융자 사업예산 신속 집행, 사업 인허가와 계통연계 과정에서 발생하는 현장의 어려움 신속 해소 등에 적극적으로 나설 방침이다."
        }
      ],
      "dedupeKey": "가동률-고유-기후부-대비-석탄화력-원전-이란발-제고",
      "clusterKey": "에너지/기후부",
      "matchedTo": null,
      "sourceName": "한겨레",
      "sourceUrl": "https://www.hani.co.kr/arti/society/environment/1248768.html",
      "publishedAt": "2026-03-11T10:20:00+00:00",
      "readTimeSec": 10,
      "status": "kept",
      "importance": 4,
      "qualityLabel": "ok",
      "qualityReason": "정보성 기사",
      "isBriefing": false
    },
    {
      "id": "2026-03-13_4",
      "date": "2026-03-13",
      "category": "에너지",
      "title": "현대건설, 북유럽서 원전 사업 기반 확대 추진",
      "summary": [
        "현대건설은 북유럽에서 현지 기업들과 신규 원전 건설 협력 방안을 논의하며 에너지 전환 사업 진출을 모색하고 있습니다.",
        "스웨덴 소형모듈원전(SMR) 사업 진출을 위해 홀텍 인터내셔널과 협력체계를 구축하고, 네덜란드 토리존과 용융염원자로(MSR) 기술 협력을 위한 협약을 체결했습니다."
      ],
      "whyImportant": "원자력 발전은 탄소 중립 목표 달성과 에너지 수요 충족에 기여할 수 있는 중요한 에너지원입니다.",
      "importanceRationale": "근거: 현대건설은 웨스팅하우스와 협력하여 북유럽 대형 원전 건설 추진을 확대하고 SMR 사업 진출을 위한 현지 협력을 다각화할 계획입니다.",
      "impactSignals": [
        {
          "label": "market-demand",
          "evidence": "현대건설 관계자는 \"최근 북유럽 국가들이 전력 수요 급증에 대응하고 온실가스 배출 제로(0)를 이행하고자 원자력에 관심을 보이고 있다\"며 \"웨스팅하우스와 협력을 바탕으로 북유럽 대형 원전 건설 추진을 확대하고 SMR 사업 진출을 위한 현지 협력을 다각화하겠다\"고 말했다."
        },
        {
          "label": "capex",
          "evidence": "현대건설은 지난 10∼11일(현지시간) 핀란드 헬싱키에서 미국 원자력 기업 웨스팅하우스와 함께 '핀란드·스웨덴 신규 원전 건설 심포지엄'을 개최했다고 12일 밝혔다."
        }
      ],
      "dedupeKey": "기반-북유럽서-사업-소형모듈원전-원전-인터내셔널-현대건설-확대",
      "clusterKey": "에너지/현대건설",
      "matchedTo": null,
      "sourceName": "연합",
      "sourceUrl": "https://www.koreancenter.or.kr/news/articleView.html?idxno=1322944",
      "publishedAt": "2026-03-12T06:29:11+00:00",
      "readTimeSec": 10,
      "status": "kept",
      "importance": 3,
      "qualityLabel": "ok",
      "qualityReason": "정보성 기사",
      "isBriefing": false
    },
    {
      "id": "2026-03-13_5",
      "date": "2026-03-13",
      "category": "에너지",
      "title": "정부, 이란 사태에 원전 조기 재가동 결정",
      "summary": [
        "정부와 더불어민주당은 이란 사태로 인한 에너지 대란 우려에 대응하여 보수 중인 원전을 조기 가동하기로 했습니다.",
        "김성환 환경부 장관은 가스 사용량 감축 및 에너지 가격 변동폭 최소화를 위해 원전 가동을 조기 복구할 것이라고 밝혔습니다.",
        "이달 신월성 1호기, 고리 2호기, 5월 중순까지 한빛 6호기 등 원전 4기를 재가동할 계획입니다."
      ],
      "whyImportant": "원전 재가동 결정은 에너지 안보 위기에 대응하고 화석 연료 의존도를 낮추려는 정부 정책의 일환으로, 향후 에너지 정책 방향에 영향을 미칠 수 있습니다.",
      "importanceRationale": "근거: 이달 신월성 1호기, 고리 2호기, 5월 중순까지 한빛 6호기 등 원전 4기 재가동 계획은 에너지 수급에 직접적인 영향을 줄 수 있습니다.",
      "impactSignals": [
        {
          "label": "market-demand",
          "evidence": "이시은 기자 see@hankyung.com 김성환 기후에너지환경부 장관은 이날 국회에서 열린 당정협의회에서 “전기료에 가장 영향을 미치는 것이 가스”라며 “가스 사용량을 줄이고 에너지 가격 변동폭을 최소화하기 위해 원전 가동을 조기 복구할 것”이라고 말했다."
        },
        {
          "label": "policy",
          "evidence": "기후에너지환경노동위원회 여당 간사인 김주영 의원은 이날 “에너지 안보 위기를 계기로 재생에너지 관련 법안을 신속히 추진할 것”이라고 말했다."
        },
        {
          "label": "capex",
          "evidence": "이 밖에 당정은 공공소각시설 확충사업 기간을 최대 3년6개월 단축하는 방안도 본격화하기로 했다."
        }
      ],
      "dedupeKey": "1호기-사태-원전-이란-재가동-정부-조기-환경부",
      "clusterKey": "에너지/사태",
      "matchedTo": null,
      "sourceName": "한국경제",
      "sourceUrl": "https://www.hankyung.com/article/2026031273861",
      "publishedAt": "2026-03-12T09:08:32+00:00",
      "readTimeSec": 10,
      "status": "kept",
      "importance": 3,
      "qualityLabel": "ok",
      "qualityReason": "정보성 기사",
      "isBriefing": false
    },
    {
      "id": "2026-03-13_6",
      "date": "2026-03-13",
      "category": "에너지",
      "title": "유럽 최초의 마이크로그리드 연결 데이터 센터 가동",
      "summary": [
        "아일랜드 더블린 외곽에 유럽 최초로 독립형 마이크로그리드에 연결된 데이터 센터가 가동되었습니다.",
        "P e Data C e G oup은 AVK와 협력하여 더블린 시설을 구축했으며, 이는 유럽의 자체 전력 생태계를 향한 첫걸음이 될 수 있습니다.",
        "이 데이터 센터는 클라우드 및 AI 워크로드를 처리할 수 있으며, 총 용량은 약 110MW이고 총 투자액은 약 10억 유로입니다."
      ],
      "whyImportant": "데이터 센터의 전력 공급 문제를 해결하기 위한 마이크로그리드 도입은 전력 인프라에 대한 새로운 접근 방식을 제시합니다.",
      "importanceRationale": "근거: 유럽연합은 2040년까지 최소 1조 2천억 유로의 투자가 필요하며, 아일랜드 데이터 센터는 2024년에 국가 전력의 22%를 소비했습니다.",
      "impactSignals": [
        {
          "label": "policy",
          "evidence": "\"We are a true enabling factor to allow big renewable projects to come online, to allow flexibility into the grid, and ultimately to allow power costs to come down for all consumers, both business and normal citizens, but the policy and regulation takes a while to allow and facilitate that,\" Childs told CNBC."
        },
        {
          "label": "capex",
          "evidence": "However, to get the most sustainable solution and to provide services back into the grid in Dublin, in the most constrained area of Ireland, it would be our desire to get a grid connection.\" The Dublin data center, which can run both cloud and AI workloads, has a total capacity of about 110 megawatts."
        },
        {
          "label": "market-demand",
          "evidence": "has such a high demand that we've seen the rollout a little bit quicker than we've seen here in Europe,\" Pritchard told CNBC, adding that the company is now seeing a new type of investor who is specifically interested in microgrids and not necessarily the data center itself."
        }
      ],
      "dedupeKey": "110mw이고-가동-데이터-마이크로그리드-센터-연결-유럽-최초",
      "clusterKey": "최초/마이크로그리드/연결",
      "matchedTo": null,
      "sourceName": "CNBC",
      "sourceUrl": "https://www.cnbc.com/2026/03/11/data-center-microgrid-power-ireland-ai-boom-avk-pure-dc.html",
      "publishedAt": "2026-03-11T06:00:01+00:00",
      "readTimeSec": 10,
      "status": "kept",
      "importance": 4,
      "qualityLabel": "ok",
      "qualityReason": "정보성 기사",
      "isBriefing": false
    },
    {
      "id": "2026-03-13_7",
      "date": "2026-03-13",
      "category": "에너지",
      "title": "현대건설, 북유럽 원전 시장 공략 가속화",
      "summary": [
        "현대건설은 웨스팅하우스와 함께 핀란드와 스웨덴에서 신규 원전 건설 심포지엄을 개최했습니다.",
        "네덜란드 원자력 기업 토리존과는 소형모듈원자로 기술 협력을 위한 업무협약을 체결했습니다.",
        "북유럽 국가들의 전력 수요 증가에 대응하여 원전 건설 추진을 확대할 계획입니다."
      ],
      "whyImportant": "이번 북유럽 원전 시장 공략은 현대건설의 해외 시장 확장과 에너지 전환에 기여할 수 있습니다.",
      "importanceRationale": "근거: 현대건설은 웨스팅하우스와 핀란드 국영 에너지 기업 '포툼'과 원전 건설을 위한 사전업무착수계약(EWA)을 체결하는 등 협력하고 있어 중요도 3으로 판단됩니다.",
      "impactSignals": [
        {
          "label": "capex",
          "evidence": "현대건설 관계자는 “최근 핀란드와 스웨덴을 비롯한 북유럽 국가들이 급증하는 전력 수요에 대응하고 있다”며 “북유럽 대형 원전 건설 추진을 확대하겠다”고 말했다."
        }
      ],
      "dedupeKey": "가속화-공략-기업-북유럽-시장-원전-웨스팅하우스-현대건설",
      "clusterKey": "에너지/현대건설",
      "matchedTo": null,
      "sourceName": "한국경제",
      "sourceUrl": "https://www.hankyung.com/article/202603126743i",
      "publishedAt": "2026-03-12T06:06:40+00:00",
      "readTimeSec": 10,
      "status": "kept",
      "importance": 3,
      "qualityLabel": "ok",
      "qualityReason": "정보성 기사",
      "isBriefing": false
    },
    {
      "id": "2026-03-13_8",
      "date": "2026-03-13",
      "category": "국제",
      "title": "미국 무역법 301조, 슈퍼 301조와 차이점",
      "summary": [
        "미국이 외국 정부의 불공정 무역 관행에 대해 보복 조치를 할 수 있는 무역법 301조를 발동했습니다.",
        "트럼프 행정부는 중국, 유럽연합 등에 301조를 적용했으며, 바이든 행정부도 대중국 관세를 유지하고 있습니다.",
        "슈퍼 301조와 달리, 301조는 불공정 무역 국가를 선별해 우선협상대상국으로 지정하지 않습니다."
      ],
      "whyImportant": "미국의 무역법 301조 발동은 특정 국가에 대한 무역 제재로 이어져 국제 무역 관계에 영향을 미칠 수 있습니다.",
      "importanceRationale": "근거: 트럼프 행정부는 2017년 중국에 301조를 처음 발동했고, 바이든 행정부도 중국산 전기차 등에 이를 적용하고 있어 정책 변화 가능성이 있습니다.",
      "impactSignals": [
        {
          "label": "security",
          "evidence": "트럼프 대통령은 집권 1기이던 2017년 8월 지식재산권 침해와 강압적인 기술 이전 요구 문제를 들어 중국을 대상으로 301조를 처음 발동했다."
        }
      ],
      "dedupeKey": "301조-무역법-미국-슈퍼-외국-우선협상대상국-정부-차이점",
      "clusterKey": "미중_법집행/무역법/관세",
      "matchedTo": null,
      "sourceName": "한겨레",
      "sourceUrl": "https://www.hani.co.kr/arti/international/america/1249027.html",
      "publishedAt": "2026-03-12T11:53:00+00:00",
      "readTimeSec": 10,
      "status": "kept",
      "importance": 3,
      "qualityLabel": "ok",
      "qualityReason": "정보성 기사",
      "isBriefing": false
    },
    {
      "id": "2026-03-13_9",
      "date": "2026-03-13",
      "category": "기술",
      "title": "엔비디아, 네비우스에 20억 달러 투자 발표 후 주가 16% 급등",
      "summary": [
        "엔비디아가 인공지능 클라우드 기업 네비우스 그룹에 20억 달러를 투자한다고 발표했습니다.",
        "이번 계약의 일환으로 양사는 AI 인프라 구축, 플릿 관리, 추론 및 AI 공장 설계 및 지원에 협력할 예정입니다.",
        "엔비디아는 2030년 말까지 5기가와트 이상의 용량을 구축할 계획입니다."
      ],
      "whyImportant": "이번 투자는 AI 클라우드 시장에서의 경쟁 심화와 기술 혁신을 가속화할 수 있기 때문입니다.",
      "importanceRationale": "근거: 엔비디아가 네비우스에 20억 달러를 투자하고, 2030년 말까지 5기가와트 이상의 용량을 구축할 계획을 발표하여 AI 인프라 확장에 대한 투자를 확대하고 있습니다.",
      "impactSignals": [
        {
          "label": "market-demand",
          "evidence": "\"Together, we are scaling the cloud to meet the surging global demand for intelligence.\""
        }
      ],
      "dedupeKey": "20억-5기가와트-급등-네비우스-달러-엔비디아-주가-투자",
      "clusterKey": "투자/ai/엔비디아",
      "matchedTo": null,
      "sourceName": "CNBC",
      "sourceUrl": "https://www.cnbc.com/2026/03/11/nebius-nvidia-ai-cloud.html",
      "publishedAt": "2026-03-11T12:17:06+00:00",
      "readTimeSec": 10,
      "status": "kept",
      "importance": 4,
      "qualityLabel": "ok",
      "qualityReason": "정보성 기사",
      "isBriefing": false
    },
    {
      "id": "2026-03-13_10",
      "date": "2026-03-13",
      "category": "에너지",
      "title": "한·미 원자력협력 정부대표, 한국 원전 공급망 강화 계획 발표",
      "summary": [
        "임갑수 한·미 원자력협력 정부대표는 국제회의에서 한국의 원전 공급망 강화 계획을 발표했습니다.",
        "최근 국내 대형원전 2기와 소형모듈원자로(SMR) 1기 건설 추진 결정 등을 설명하며 수출 경쟁력을 높일 것이라고 밝혔습니다."
      ],
      "whyImportant": "원자력 에너지의 중요성이 부각되는 시점에서 한국의 원전 공급망 강화는 에너지 안보 및 수출 경쟁력 측면에서 중요한 의미를 가집니다.",
      "importanceRationale": "근거: 한국이 대형원전 2기와 SMR 1기 건설을 추진하기로 결정한 점을 언급하며 공급망 강화 계획을 밝혔기 때문입니다.",
      "impactSignals": [
        {
          "label": "market-demand",
          "evidence": "임 대표는 기후변화와 에너지 안보, 인공지능 시대 전력수요 급증, 불안정한 중동 정세 속에서 “원자력 에너지는 기후변화 대응과 에너지 안보를 동시에 달성할 수 있는 핵심 에너지원”이라고 강조했다."
        }
      ],
      "dedupeKey": "1기-2기-강화-공급망-원자력협력-원전-정부대표-한국",
      "clusterKey": "에너지/원자력협력",
      "matchedTo": null,
      "sourceName": "한겨레",
      "sourceUrl": "https://www.hani.co.kr/arti/politics/politics_general/1248764.html",
      "publishedAt": "2026-03-11T04:36:00+00:00",
      "readTimeSec": 10,
      "status": "kept",
      "importance": 3,
      "qualityLabel": "ok",
      "qualityReason": "정보성 기사",
      "isBriefing": false
    }
  ]
}